TermART/__init__.py
termart-0.1.1.dist-info/licenses/LICENSE
termart-0.1.1.dist-info/METADATA
termart-0.1.1.dist-info/WHEEL
termart-0.1.1.dist-info/top_level.txt
termart-0.1.1.dist-info/RECORD
