Metadata-Version: 2.4
Name: TermART
Version: 0.1.1
Summary: A cool terminal formatting tool
Author-email: CHINmcl <namning670@gmail.com>
License: MIT
License-File: LICENSE
Requires-Dist: pyfiglet==1.0.2
Dynamic: license-file
